.DS_Store
MANIFEST.in
README.md
push.sh
redis_maintainer.py
setup.py
.git/COMMIT_EDITMSG
.git/FETCH_HEAD
.git/HEAD
.git/ORIG_HEAD
.git/config
.git/description
.git/index
.git/hooks/applypatch-msg.sample
.git/hooks/commit-msg.sample
.git/hooks/fsmonitor-watchman.sample
.git/hooks/post-update.sample
.git/hooks/pre-applypatch.sample
.git/hooks/pre-commit.sample
.git/hooks/pre-merge-commit.sample
.git/hooks/pre-push.sample
.git/hooks/pre-rebase.sample
.git/hooks/pre-receive.sample
.git/hooks/prepare-commit-msg.sample
.git/hooks/push-to-checkout.sample
.git/hooks/update.sample
.git/info/exclude
.git/logs/HEAD
.git/logs/refs/heads/master
.git/logs/refs/remotes/origin/HEAD
.git/logs/refs/remotes/origin/master
.git/objects/00/41c04b20be6b4bbd75a815bebf7084805f8712
.git/objects/01/cab3024759cc906cee0a6a3429918f5b63fabc
.git/objects/04/11b566ad4fa2d7dedd4026ac3a1aa81583f063
.git/objects/04/39e3d2d63962999b7b1a118029bac2b28340c7
.git/objects/04/8be6a509c9c6b3cd9d24bf7d2f04e8614144c9
.git/objects/05/1acb58a6d6c6dbb4150bf9221569e1912eb5bc
.git/objects/05/77692fdce48e2fd5c28dac0eacda2b48e87ca6
.git/objects/08/ea4e268e6f806a7f000c9ae9f7d48f4a770cd9
.git/objects/0a/1bedc205741de440716866d33eb08b3e235ead
.git/objects/0a/9d72ddc75f5c6b4f481ee66afc8fd420e1ad69
.git/objects/0b/9c91dcf98edb3b3bf9ab9474944a29b6868823
.git/objects/0b/d87a6d4f13f0b8b442be5ebf677f5207f15d03
.git/objects/0c/1fe034db405fb5c649a2e85afc24dcd8dafa78
.git/objects/0e/24281e6a23a799bba50234909a4eefc062407f
.git/objects/0e/3fb35ffbadaf084a2915cfc29e9f63d8dc0b80
.git/objects/0e/81dec5c311e0f1902b5a7476df00bf787b727d
.git/objects/10/5ce2da2d6447d11dfe32bfb846c3d5b199fc99
.git/objects/11/99c39684aa7eae02b2548d627fa77c23648e89
.git/objects/11/f13a31edccde503893c6083b99d6243e26f111
.git/objects/12/c371931538565d632db7e70841c6dd81e6a5e6
.git/objects/14/2068ef3450523a0e5f073bd62eec3746405639
.git/objects/17/00d635be40b3166177cbcddfaf61289d501fe6
.git/objects/18/306db2edfa5e87d02c8545420efe8682a8da0c
lazyinit.egg-info/PKG-INFO
lazyinit.egg-info/SOURCES.txt
lazyinit.egg-info/dependency_links.txt
lazyinit.egg-info/entry_points.txt
lazyinit.egg-info/requires.txt
lazyinit.egg-info/top_level.txt
