Metadata-Version: 2.1
Name: lazyinit
Version: 0.1.6
Summary: Init lazydl environment.
Home-page: https://github.com/deng1fan
Author: deng1fan
Author-email: dengyifan@iie.ac.cn
Requires-Python: >=3.6
